Metadata-Version: 2.4
Name: aesthetic
Version: 0.9
Summary: a e s t h e t i c
Home-page: https://github.com/lgbouma/aesthetic
Download-URL: https://github.com/lgbouma/aesthetic/archive/refs/tags/v09.tar.gz
Author: Luke Bouma
Author-email: bouma.luke@gmail.com
License: MIT
Keywords: astronomy,matplotlib-style-sheets
Classifier: Development Status :: 3 - Alpha
Classifier: License :: OSI Approved :: MIT License
Classifier: Intended Audience :: Science/Research
Classifier: Topic :: Scientific/Engineering :: Astronomy
Classifier: Operating System :: OS Independent
Classifier: Programming Language :: Python :: 3
License-File: LICENSE
Requires-Dist: matplotlib
Provides-Extra: tests
Requires-Dist: pytest==3.8.2; extra == "tests"
Dynamic: download-url
Dynamic: license-file
